annotell_base_clients-0.1.0-py3.8-nspkg.pth
annotell/base_clients/__init__.py
annotell/base_clients/http_client.py
annotell/base_clients/models.py
annotell/base_clients/util.py
annotell/base_clients/cloud_storage/__init__.py
annotell/base_clients/cloud_storage/download_handler.py
annotell/base_clients/cloud_storage/file_resource_client.py
annotell/base_clients/cloud_storage/upload_handler.py
annotell_base_clients-0.1.0.dist-info/METADATA
annotell_base_clients-0.1.0.dist-info/WHEEL
annotell_base_clients-0.1.0.dist-info/namespace_packages.txt
annotell_base_clients-0.1.0.dist-info/top_level.txt
annotell_base_clients-0.1.0.dist-info/RECORD
