Metadata-Version: 2.1
Name: annotell-base-clients
Version: 0.1.0
Summary: Annotell Base Clients
Home-page: https://github.com/annotell/annotell-python
Author: Annotell
Author-email: Interoperability <interoperability@annotell.com>
License: MIT
Download-URL: https://github.com/annotell/annotell-python/tarball/0.1.0
Keywords: API,Annotell
Platform: UNKNOWN
Classifier: Development Status :: 5 - Production/Stable
Classifier: License :: OSI Approved :: MIT License
Classifier: Intended Audience :: Developers
Classifier: Programming Language :: Python :: 3
Requires-Python: ~=3.6
Requires-Dist: annotell-auth (>=2.0.1<3)
Requires-Dist: requests (>=2.23.0)
Requires-Dist: pydantic
